[{"name":"CHROMATIC","notes":"C C# D D# E F F# G G# A A# B C","semitones":[0,1,2,3,4,5,6,7,8,9,10,11],"mode":""},{"name":"CHINESE TWELVE TONE SCALE","notes":"C G D A E B F# C# Ab Eb Bb F C","semitones":[0,7,2,9,4,11,6,1,8,3,10,5],"mode":""},{"name":"ALGERIAN","notes":"C D Eb F F# G Ab B C","semitones":[0,2,3,5,6,7,8,11],"mode":"Alerigan - mode 1"},{"name":"ALGERIAN - mode 2","notes":"C Db Eb E F Gb A Bb C","semitones":[0,1,3,4,5,6,9,10],"mode":"Alerigan - mode 2"},{"name":"ALGERIAN - mode 3","notes":"C D Eb E F G# A B C","semitones":[0,2,3,4,5,8,9,11],"mode":"Alerigan - mode 3"},{"name":"ALGERIAN - mode 4","notes":"C C# D Eb F# G A Bb C","semitones":[0,1,2,3,6,7,9,10],"mode":"Alerigan - mode 4"},{"name":"ALGERIAN - mode 5","notes":"C C# D F F# G# A B C","semitones":[0,1,2,5,6,8,9,11],"mode":"Alerigan - mode 5"},{"name":"ALGERIAN - mode 6","notes":"C C# E F G Ab Bb B C","semitones":[0,1,4,5,7,8,10,11],"mode":"Alerigan - mode 6"},{"name":"ALGERIAN - mode 7","notes":"C D# E F# G A Bb B C","semitones":[0,3,4,6,7,9,10,11],"mode":"Alerigan - mode 7"},{"name":"ALGERIAN - mode 8","notes":"C Db Eb Fb Gb G Ab A C","semitones":[0,1,3,4,6,7,8,9],"mode":"Alerigan - mode 8"},{"name":"ASYMMETRICALLY EXPANDED IONIAN SCALE","notes":"C D E F# G# A Bb B C","semitones":[0,2,4,6,8,9,10,11],"mode":"Asymmetrically Expanded Ionian Scale - mode 1"},{"name":"ASYMMETRICALLY EXPANDED IONIAN SCALE - mode 2","notes":"C D E F# G G# A Bb C","semitones":[0,2,4,6,7,8,9,10],"mode":"Asymmetrically Expanded Ionian Scale - mode 2"},{"name":"ASYMMETRICALLY EXPANDED IONIAN SCALE - mode 3","notes":"C D E F F# G Ab Bb C","semitones":[0,2,4,5,6,7,8,10],"mode":"Asymmetrically Expanded Ionian Scale - mode 3"},{"name":"ASYMMETRICALLY EXPANDED IONIAN SCALE - mode 4","notes":"C D Eb E F F# Ab Bb C","semitones":[0,2,3,4,5,6,8,10],"mode":"Asymmetrically Expanded Ionian Scale - mode 4"},{"name":"ASYMMETRICALLY EXPANDED IONIAN SCALE - mode 5","notes":"C C# D Eb E F# G# Bb C","semitones":[0,1,2,3,4,6,8,10],"mode":"Asymmetrically Expanded Ionian Scale - mode 5"},{"name":"ASYMMETRICALLY EXPANDED IONIAN SCALE - mode 6","notes":"C C# D Eb F G A B C","semitones":[0,1,2,3,5,7,9,11],"mode":"Asymmetrically Expanded Ionian Scale - mode 6"},{"name":"ASYMMETRICALLY EXPANDED IONIAN SCALE - mode 7","notes":"C C# D E F# G# Bb B C","semitones":[0,1,2,4,6,8,10,11],"mode":"Asymmetrically Expanded Ionian Scale - mode 7"},{"name":"ASYMMETRICALLY EXPANDED IONIAN SCALE - mode 8","notes":"C Db Eb F G A Bb B C","semitones":[0,1,3,5,7,9,10,11],"mode":"Asymmetrically Expanded Ionian Scale - mode 8"},{"name":"BUZURG","notes":"C Db E F F# G Ab B C","semitones":[0,1,4,5,6,7,8,11],"mode":"Buzurg - mode 1"},{"name":"BUZURG - mode 2","notes":"C D# E F F# G A# B C","semitones":[0,3,4,5,6,7,10,11],"mode":"Buzurg - mode 2"},{"name":"BUZURG - mode 3","notes":"C Db D Eb Fb G Ab A C","semitones":[0,1,2,3,4,7,8,9],"mode":"Buzurg - mode 3"},{"name":"YUSEF SYNTHETIC 7","notes":"C C# D Eb F# G Ab B C","semitones":[0,1,2,3,6,7,8,11],"mode":"Buzurg - mode 4"},{"name":"BUZURG - mode 5","notes":"C C# D F F# G A# B C","semitones":[0,1,2,5,6,7,10,11],"mode":"Buzurg - mode 5"},{"name":"BUZURG - mode 6","notes":"C Db E F Gb A Bb B C","semitones":[0,1,4,5,6,9,10,11],"mode":"Buzurg - mode 6"},{"name":"BUZURG - mode 7","notes":"C D# E F G# A A# B C","semitones":[0,3,4,5,8,9,10,11],"mode":"Buzurg - mode 7"},{"name":"BUZURG - mode 8","notes":"C C# E F F# G G# A C","semitones":[0,1,4,5,6,7,8,9],"mode":"Buzurg - mode 8"},{"name":"EIGHT TONE SPANISH","notes":"C Db Eb E F Gb Ab Bb C","semitones":[0,1,3,4,5,6,8,10],"mode":"Eight Tone Spanish - mode 1"},{"name":"EIGHT TONE SPANISH - mode 2","notes":"C D Eb E F G A B C","semitones":[0,2,3,4,5,7,9,11],"mode":"Eight Tone Spanish - mode 2"},{"name":"EIGHT TONE SPANISH - mode 3","notes":"C C# D Eb F G A Bb C","semitones":[0,1,2,3,5,7,9,10],"mode":"Eight Tone Spanish - mode 3"},{"name":"EIGHT TONE SPANISH - mode 4","notes":"C C# D E F# G# A B C","semitones":[0,1,2,4,6,8,9,11],"mode":"Eight Tone Spanish - mode 4"},{"name":"BEBOP PHRYGIAN","notes":"C Db Eb F G Ab Bb B C","semitones":[0,1,3,5,7,8,10,11],"mode":"Eight Tone Spanish - mode 5"},{"name":"BEBOP LYDIAN DOMINANT","notes":"C D E F# G A Bb B C","semitones":[0,2,4,6,7,9,10,11],"mode":"Eight Tone Spanish - mode 6"},{"name":"EIGHT TONE SPANISH - mode 7","notes":"C D E F G Ab A Bb C","semitones":[0,2,4,5,7,8,9,10],"mode":"Eight Tone Spanish - mode 7"},{"name":"EIGHT TONE SPANISH - mode 8","notes":"C D Eb F Gb G Ab Bb C","semitones":[0,2,3,5,6,7,8,10],"mode":"Eight Tone Spanish - mode 8"},{"name":"BEBOP MAJOR","notes":"C D E F G G# A B C","semitones":[0,2,4,5,7,8,9,11],"mode":"Bebop Major - mode 1"},{"name":"BEBOP MAJOR - mode 2","notes":"C D Eb F F# G A Bb C","semitones":[0,2,3,5,6,7,9,10],"mode":"Bebop Major - mode 2"},{"name":"BEBOP MAJOR - mode 3","notes":"C Db Eb E F G Ab Bb C","semitones":[0,1,3,4,5,7,8,10],"mode":"Bebop Major - mode 3"},{"name":"BEBOP MAJOR - mode 4","notes":"C D D# E F# G A B C","semitones":[0,2,3,4,6,7,9,11],"mode":"Bebop Major - mode 4"},{"name":"BEBOP MAJOR - mode 5","notes":"C C# D E F G A Bb C","semitones":[0,1,2,4,5,7,9,10],"mode":"Bebop Major - mode 5"},{"name":"BEBOP MAJOR - mode 6","notes":"C C# D# E F# G# A B C","semitones":[0,1,3,4,6,8,9,11],"mode":"Bebop Major - mode 6"},{"name":"BEBOP NATURAL MINOR, ISFAHAN 2","notes":"C D Eb F G Ab Bb B C","semitones":[0,2,3,5,7,8,10,11],"mode":"Bebop Major - mode 7"},{"name":"BEBOP MAJOR - mode 8","notes":"C Db Eb F Gb Ab A Bb C","semitones":[0,1,3,5,6,8,9,10],"mode":"Bebop Major - mode 8"},{"name":"BEBOP DOMINANT","notes":"C D E F G A Bb B C","semitones":[0,2,4,5,7,9,10,11],"mode":"Bebop Dominant - mode 1"},{"name":"BEBOP DOMINANT - mode 2","notes":"C D Eb F G Ab A Bb C","semitones":[0,2,3,5,7,8,9,10],"mode":"Bebop Dominant - mode 2"},{"name":"BEBOP DOMINANT - mode 3","notes":"C Db Eb F Gb G Ab Bb C","semitones":[0,1,3,5,6,7,8,10],"mode":"Bebop Dominant - mode 3"},{"name":"BEBOP DOMINANT - mode 4","notes":"C D E F F# G A B C","semitones":[0,2,4,5,6,7,9,11],"mode":"Bebop Dominant - mode 4"},{"name":"BEBOP DOMINANT - mode 5","notes":"C D Eb E F G A Bb C","semitones":[0,2,3,4,5,7,9,10],"mode":"Bebop Dominant - mode 5"},{"name":"BEBOP DOMINANT - mode 6","notes":"C Db D Eb F G Ab Bb C","semitones":[0,1,2,3,5,7,8,10],"mode":"Bebop Dominant - mode 6"},{"name":"BEBOP DOMINANT - mode 7","notes":"C C# D E F# G A B C","semitones":[0,1,2,4,6,7,9,11],"mode":"Bebop Dominant - mode 7"},{"name":"BEBOP LOCRIAN, IRAQ","notes":"C Db Eb F Gb Ab Bb B C","semitones":[0,1,3,5,6,8,10,11],"mode":"Bebop Dominant - mode 8"},{"name":"BEBOP DORIAN - ISFAHAN 1","notes":"C D Eb F G A Bb B C","semitones":[0,2,3,5,7,9,10,11],"mode":"Bebop Dorian - mode 1"},{"name":"BEBOP DORIAN - mode 2","notes":"C Db Eb F G Ab A Bb C","semitones":[0,1,3,5,7,8,9,10],"mode":"Bebop Dorian - mode 2"},{"name":"BEBOP LYDIAN","notes":"C D E F# G G# A B C","semitones":[0,2,4,6,7,8,9,11],"mode":"Bebop Dorian - mode 3"},{"name":"BEBOP DORIAN - mode 4","notes":"C D E F F# G A Bb C","semitones":[0,2,4,5,6,7,9,10],"mode":"Bebop Dorian - mode 4"},{"name":"BEBOP DORIAN - mode 5","notes":"C D Eb E F G Ab Bb C","semitones":[0,2,3,4,5,7,8,10],"mode":"Bebop Dorian - mode 5"},{"name":"BEBOP DORIAN - mode 6","notes":"C Db D Eb F Gb Ab Bb C","semitones":[0,1,2,3,5,6,8,10],"mode":"Bebop Dorian - mode 6"},{"name":"BEBOP DORIAN - mode 7","notes":"C C# D E F G A B C","semitones":[0,1,2,4,5,7,9,11],"mode":"Bebop Dorian - mode 7"},{"name":"BEBOP ALTERED","notes":"C C# D# E F# G# A# B C","semitones":[0,1,3,4,6,8,10,11],"mode":"Bebop Dorian - mode 8"},{"name":"BEBOP MELODIC MINOR","notes":"C D Eb F G G# A B C","semitones":[0,2,3,5,7,8,9,11],"mode":"Bebop Melodic Minor - mode 1"},{"name":"BEBOP MELODIC MINOR - mode 2","notes":"C Db Eb F F# G A Bb C","semitones":[0,1,3,5,6,7,9,10],"mode":"Bebop Melodic Minor - mode 2"},{"name":"BEBOP MELODIC MINOR - mode 3","notes":"C D E F F# G# A B C","semitones":[0,2,4,5,6,8,9,11],"mode":"Bebop Melodic Minor - mode 3"},{"name":"BEBOP MELODIC MINOR - mode 4","notes":"C D D# E F# G A Bb C","semitones":[0,2,3,4,6,7,9,10],"mode":"Bebop Melodic Minor - mode 4"},{"name":"BEBOP MELODIC MINOR - mode 5","notes":"C C# D E F G Ab Bb C","semitones":[0,1,2,4,5,7,8,10],"mode":"Bebop Melodic Minor - mode 5"},{"name":"BEBOP MELODIC MINOR - mode 6","notes":"C C# D# E F# G A B C","semitones":[0,1,3,4,6,7,9,11],"mode":"Bebop Melodic Minor - mode 6"},{"name":"BEBOP HALF DIMINISHED","notes":"C D Eb F Gb Ab Bb B C","semitones":[0,2,3,5,6,8,10,11],"mode":"Bebop Melodic Minor - mode 7"},{"name":"BEBOP MELODIC MINOR - mode 8","notes":"C C# D# E F# G# A Bb C","semitones":[0,1,3,4,6,8,9,10],"mode":"Bebop Melodic Minor - mode 8"},{"name":"IONIAN","notes":"C D E F G A B C","semitones":[0,2,4,5,7,9,11],"mode":"Major - mode 1"},{"name":"DORIAN","notes":"C D Eb F G A Bb C","semitones":[0,2,3,5,7,9,10],"mode":"Major - mode 2"},{"name":"PHRYGIAN","notes":"C Db Eb F G Ab Bb C","semitones":[0,1,3,5,7,8,10],"mode":"Major - mode 3"},{"name":"LYDIAN","notes":"C D E F# G A B C","semitones":[0,2,4,6,7,9,11],"mode":"Major - mode 4"},{"name":"MIXOLYDIAN","notes":"C D E F G A Bb C","semitones":[0,2,4,5,7,9,10],"mode":"Major - mode 5"},{"name":"AEOLIAN, NATURAL MINOR","notes":"C D Eb F G Ab Bb C","semitones":[0,2,3,5,7,8,10],"mode":"Major - mode 6"},{"name":"LOCRIAN","notes":"C Db Eb F Gb Ab Bb C","semitones":[0,1,3,5,6,8,10],"mode":"Major - mode 7"},{"name":"HARMONIC MAJOR","notes":"C D E F G Ab B C","semitones":[0,2,4,5,7,8,11],"mode":"Harmonic Major - mode 1"},{"name":"DORIAN b5, ZANGULA","notes":"C D Eb F Gb A Bb C","semitones":[0,2,3,5,6,9,10],"mode":"Harmonic Major - mode 2"},{"name":"PHRYGIAN b4","notes":"C Db Eb Fb G Ab Bb C","semitones":[0,1,3,4,7,8,10],"mode":"Harmonic Major - mode 3"},{"name":"LYDIAN b3","notes":"C D Eb F# G A B C","semitones":[0,2,3,6,7,9,11],"mode":"Harmonic Major - mode 4"},{"name":"MIXOLYDIAN b2","notes":"C Db E F G A Bb C","semitones":[0,1,4,5,7,9,10],"mode":"Harmonic Major - mode 5"},{"name":"LYDIAN #2 #5","notes":"C D# E F# G# A B C","semitones":[0,3,4,6,8,9,11],"mode":"Harmonic Major - mode 6"},{"name":"LOCRIAN b7","notes":"C Db Eb F Gb Ab Bbb C","semitones":[0,1,3,5,6,8,9],"mode":"Harmonic Major - mode 7"},{"name":"MELODIC MINOR","notes":"C D Eb F G A B C","semitones":[0,2,3,5,7,9,11],"mode":"Melodic Minor - mode 1"},{"name":"DORIAN b2","notes":"C Db Eb F G A Bb C","semitones":[0,1,3,5,7,9,10],"mode":"Melodic Minor - mode 2"},{"name":"LYDIAN AUGMENTED","notes":"C D E F# G# A B C","semitones":[0,2,4,6,8,9,11],"mode":"Melodic Minor - mode 3"},{"name":"LYDIAN DOMINANT","notes":"C D E F# G A Bb C","semitones":[0,2,4,6,7,9,10],"mode":"Melodic Minor - mode 4"},{"name":"MIXOLYDIAN b6, HINDU","notes":"C D E F G Ab Bb C","semitones":[0,2,4,5,7,8,10],"mode":"Melodic Minor - mode 5"},{"name":"LOCRIAN #2","notes":"C D Eb F Gb Ab Bb C","semitones":[0,2,3,5,6,8,10],"mode":"Melodic Minor - mode 6"},{"name":"SUPER LOCRIAN, ALTERED SCALE","notes":"C Db Eb Fb Gb Ab Bb C","semitones":[0,1,3,4,6,8,10],"mode":"Melodic Minor - mode 7"},{"name":"HARMONIC MINOR","notes":"C D Eb F G Ab B C","semitones":[0,2,3,5,7,8,11],"mode":"Harmonic Minor - mode 1"},{"name":"LOCRIAN #6, HIJAZI","notes":"C Db Eb F Gb A Bb C","semitones":[0,1,3,5,6,9,10],"mode":"Harmonic Minor - mode 2"},{"name":"IONIAN #5","notes":"C D E F G# A B C","semitones":[0,2,4,5,8,9,11],"mode":"Harmonic Minor - mode 3"},{"name":"DORIAN #4, UKRAINIAN, HUNGARIAN","notes":"C D Eb F# G A Bb C","semitones":[0,2,3,6,7,9,10],"mode":"Harmonic Minor - mode 4"},{"name":"PHRYGIAN #3, PHYRGIAN DOMINANT, SPANISH GYPSY, HEBREW","notes":"C Db E F G Ab Bb C","semitones":[0,1,4,5,7,8,10],"mode":"Harmonic Minor - mode 5"},{"name":"LYDIAN #2, MAQAM MUSTAR","notes":"C D# E F# G A B C","semitones":[0,3,4,6,7,9,11],"mode":"Harmonic Minor - mode 6"},{"name":"LOCRIAN b4 b7","notes":"C Db Eb Fb Gb Ab Bbb C","semitones":[0,1,3,4,6,8,9],"mode":"Harmonic Minor - mode 7"},{"name":"DOUBLE HARMONIC, BYZANTINE, PERSIAN","notes":"C Db E F G Ab B C","semitones":[0,1,4,5,7,8,11],"mode":"Double Harmonic - mode 1"},{"name":"YUSEF SYNTHETIC 2","notes":"C D# E F# G A# B C","semitones":[0,3,4,6,7,10,11],"mode":"Double Harmonic - mode 2"},{"name":"DOUBLE HARMONIC - mode 3","notes":"C Db Eb Fb G Ab Abb C","semitones":[0,1,3,4,7,8,7],"mode":"Double Harmonic - mode 3"},{"name":"LYDIAN b3 b6, HUNGARIAN GYPSY, EGYPTIAN","notes":"C D Eb F# G Ab B C","semitones":[0,2,3,6,7,8,11],"mode":"Double Harmonic - mode 4"},{"name":"DOUBLE HARMONIC - mode 5","notes":"C Db E F Gb A Bb C","semitones":[0,1,4,5,6,9,10],"mode":"Double Harmonic - mode 5"},{"name":"DOUBLE HARMONIC - mode 6","notes":"C D# E F G# A B C","semitones":[0,3,4,5,8,9,11],"mode":"Double Harmonic - mode 6"},{"name":"DOUBLE HARMONIC - mode 7","notes":"C Db Ebb F Gb Ab Bbb C","semitones":[0,1,2,5,6,8,9],"mode":"Double Harmonic - mode 7"},{"name":"HUNGARIAN BLUE SCALE","notes":"C D Eb F F# G# A C","semitones":[0,2,3,5,6,8,9],"mode":"Hungarian Blue Scale - mode 1"},{"name":"HUNGARIAN BLUE SCALE - mode 2","notes":"C C# D# E F# G Bb C","semitones":[0,1,3,4,6,7,10],"mode":"Hungarian Blue Scale - mode 2"},{"name":"HUNGARIAN BLUE SCALE - mode 3","notes":"C D Eb F F# A Bb C","semitones":[0,2,3,5,6,9,10],"mode":"Hungarian Blue Scale - mode 3"},{"name":"HUNGARIAN BLUE SCALE - mode 4","notes":"C C# D# E G A Bb C","semitones":[0,1,3,4,7,9,10],"mode":"Hungarian Blue Scale - mode 4"},{"name":"HUNGARIAN BLUE SCALE - mode 5","notes":"C D Eb F# G# A B C","semitones":[0,2,3,6,8,9,11],"mode":"Hungarian Blue Scale - mode 5"},{"name":"HUNGARIAN BLUE SCALE - mode 6","notes":"C C# E F# G A Bb C","semitones":[0,1,4,6,7,9,10],"mode":"Hungarian Blue Scale - mode 6"},{"name":"HUNGARIAN BLUE SCALE - mode 7","notes":"C Eb F F# G# A B C","semitones":[0,3,5,6,8,9,11],"mode":"Hungarian Blue Scale - mode 7"},{"name":"ZIRAFKAND, LOCRIAN HARMONIC","notes":"C Db Eb F Gb Ab B C","semitones":[0,1,3,5,6,8,11],"mode":"Zirafkand - mode 1"},{"name":"ZIRAFKAND - mode 2","notes":"C D E F G A# B C","semitones":[0,2,4,5,7,10,11],"mode":"Zirafkand - mode 2"},{"name":"ZIRAFKAND - mode 3","notes":"C D Eb F G# A Bb C","semitones":[0,2,3,5,8,9,10],"mode":"Zirafkand - mode 3"},{"name":"ZIRAFKAND - mode 4","notes":"C Db Eb F# G Ab Bb C","semitones":[0,1,3,6,7,8,10],"mode":"Zirafkand - mode 4"},{"name":"ZIRAFKAND - mode 5","notes":"C D F F# G A B C","semitones":[0,2,5,6,7,9,11],"mode":"Zirafkand - mode 5"},{"name":"ZIRAFKAND - mode 6","notes":"C D# E F G A Bb C","semitones":[0,3,4,5,7,9,10],"mode":"Zirafkand - mode 6"},{"name":"ZIRAFKAND - mode 7","notes":"C C# D E F# G A C","semitones":[0,1,2,4,6,7,9],"mode":"Zirafkand - mode 7"},{"name":"WHOLE TONE BEBOP, LEADING WHOLE TONE","notes":"C D E F# G# A# B C","semitones":[0,2,4,6,8,10,11],"mode":"Leading Whole Tone - mode 1"},{"name":"WHOLE TONE BEBOP - mode 2","notes":"C D E F# G# A Bb C","semitones":[0,2,4,6,8,9,10],"mode":"Leading Whole Tone - mode 2"},{"name":"LYDIAN MINOR","notes":"C D E F# G Ab Bb C","semitones":[0,2,4,6,7,8,10],"mode":"Leading Whole Tone - mode 3"},{"name":"MAJOR LOCRIAN, ARABIC","notes":"C D E F Gb Ab Bb C","semitones":[0,2,4,5,6,8,10],"mode":"Leading Whole Tone - mode 4"},{"name":"WHOLE TONE BEBOP - mode 5","notes":"C D Eb Fb Gb Ab Bb C","semitones":[0,2,3,4,6,8,10],"mode":"Leading Whole Tone - mode 5"},{"name":"WHOLE TONE BEBOP - mode 6","notes":"C C# D E F# Ab Bb C","semitones":[0,1,2,4,6,8,10],"mode":"Leading Whole Tone - mode 6"},{"name":"NEAPOLITAN MAJOR","notes":"C Db Eb F G A B C","semitones":[0,1,3,5,7,9,11],"mode":"Leading Whole Tone - mode 7"},{"name":"NEAPOLITAN MINOR, HARMONIC PHRYGIAN","notes":"C Db Eb F G Ab B C","semitones":[0,1,3,5,7,8,11],"mode":"Harmonic Phyrgian - mode 1"},{"name":"HARMONIC PHRYGIAN - mode 2","notes":"C D E F# G A# B C","semitones":[0,2,4,6,7,10,11],"mode":"Harmonic Phyrgian - mode 2"},{"name":"YUSEF SYNTHETIC 4","notes":"C D E F G# A Bb C","semitones":[0,2,4,5,8,9,10],"mode":"Harmonic Phyrgian - mode 3"},{"name":"HARMONIC PHRYGIAN - mode 4","notes":"C D Eb F# G Ab Bb C","semitones":[0,2,3,6,7,8,10],"mode":"Harmonic Phyrgian - mode 4"},{"name":"RAHAWI","notes":"C Db E F Gb Ab Bb C","semitones":[0,1,4,5,6,8,10],"mode":"Harmonic Phyrgian - mode 5"},{"name":"HARMONIC PHRYGIAN - mode 6","notes":"C D# E F G A B C","semitones":[0,3,4,5,7,9,11],"mode":"Harmonic Phyrgian - mode 6"},{"name":"HARMONIC PHRYGIAN - mode 7","notes":"C C# D E F# G# A C","semitones":[0,1,2,4,6,8,9],"mode":"Harmonic Phyrgian - mode 7"},{"name":"LYDIAN HARMONIC","notes":"C D E F# G Ab B C","semitones":[0,2,4,6,7,8,11],"mode":"Lydian Harmonic - mode 1"},{"name":"DOMINANT b5","notes":"C D E F Gb A Bb C","semitones":[0,2,4,5,6,9,10],"mode":"Lydian Harmonic - mode 2"},{"name":"AEOLIAN DIMINISHED 4","notes":"C D Eb Fb G Ab Bb C","semitones":[0,2,3,4,7,8,10],"mode":"Lydian Harmonic - mode 3"},{"name":"LOCRIAN b3","notes":"C C# D F Gb Ab Bb","semitones":[0,1,2,5,6,8],"mode":"Lydian Harmonic - mode 4"},{"name":"MAJOR b2","notes":"C Db E F G A B C","semitones":[0,1,4,5,7,9,11],"mode":"Lydian Harmonic - mode 5"},{"name":"LYDIAN #2 #5 #6","notes":"C D# E F# G# A# B C","semitones":[0,3,4,6,8,10,11],"mode":"Lydian Harmonic - mode 6"},{"name":"PHRYGIAN b7","notes":"C Db Eb F G Ab A C","semitones":[0,1,3,5,7,8,9],"mode":"Lydian Harmonic - mode 7"},{"name":"NOH","notes":"C D F G G# A B C","semitones":[0,2,5,7,8,9,11],"mode":"Noh - mode 1"},{"name":"NOH - mode 2","notes":"C Eb F F# G A Bb C","semitones":[0,3,5,6,7,9,10],"mode":"Noh - mode 2"},{"name":"NOH - mode 3","notes":"C D D# E F# G A C","semitones":[0,2,3,4,6,7,9],"mode":"Noh - mode 3"},{"name":"NOH - mode 4","notes":"C C# D E F G Bb C","semitones":[0,1,2,4,5,7,10],"mode":"Noh - mode 4"},{"name":"NOH - mode 5","notes":"C C# D# E F# A B C","semitones":[0,1,3,4,6,9,11],"mode":"Noh - mode 5"},{"name":"NOH - mode 6","notes":"C D Eb F Ab Bb B C","semitones":[0,2,3,5,8,10,11],"mode":"Noh - mode 6"},{"name":"NOH - mode 7","notes":"C Db Eb Gb Ab A Bb C","semitones":[0,1,3,6,8,9,10],"mode":"Noh - mode 7"},{"name":"SRI, PURVI","notes":"C Db E F# G Ab B C","semitones":[0,1,4,6,7,8,11],"mode":"Sri - mode 1"},{"name":"SRI - mode 2","notes":"C Eb F F# G A# B C","semitones":[0,3,5,6,7,10,11],"mode":"Sri - mode 2"},{"name":"SRI - mode 3","notes":"C D Eb Fb G Ab A C","semitones":[0,2,3,4,7,8,9],"mode":"Sri - mode 3"},{"name":"SRI - mode 4","notes":"C C# D F F# G Bb C","semitones":[0,1,2,5,6,7,10],"mode":"Sri - mode 4"},{"name":"SRI - mode 5","notes":"C Db E F Gb A B C","semitones":[0,1,4,5,6,9,11],"mode":"Sri - mode 5"},{"name":"SRI - mode 6","notes":"C D# E F G# A# B C","semitones":[0,3,4,5,8,10,11],"mode":"Sri - mode 6"},{"name":"SRI - mode 7","notes":"C C# D F G Ab A C","semitones":[0,1,2,5,7,8,9],"mode":"Sri - mode 7"},{"name":"TODI","notes":"C Db Eb F# G Ab B C","semitones":[0,1,3,6,7,8,11],"mode":"Todi - mode 1"},{"name":"TODI - mode 2","notes":"C D F F# G A# B C","semitones":[0,2,5,6,7,10,11],"mode":"Todi - mode 2"},{"name":"TODI - mode 3","notes":"C D# E F G# A Bb","semitones":[0,3,4,5,8,9],"mode":"Todi - mode 3"},{"name":"TODI - mode 4","notes":"C C# D E# F# G A C","semitones":[0,1,2,5,6,7,9],"mode":"Todi - mode 4"},{"name":"TODI - mode 5","notes":"C Db E F Gb Ab B C","semitones":[0,1,4,5,6,8,11],"mode":"Todi - mode 5"},{"name":"TODI - mode 6","notes":"C D# E F G A# B C","semitones":[0,3,4,5,7,10,11],"mode":"Todi - mode 6"},{"name":"TODI - mode 7","notes":"C C# D E G G# A C","semitones":[0,1,2,4,7,8,9],"mode":"Todi - mode 7"},{"name":"ENIGMATIC 1","notes":"C Db E Gb Ab Bb B C","semitones":[0,1,4,6,8,10,11],"mode":"Enigmatic 1 - mode 1"},{"name":"ENIGMATIC 1 - mode 2","notes":"C Eb F G A A# B C","semitones":[0,3,5,7,9,10,11],"mode":"Enigmatic 1 - mode 2"},{"name":"ENIGMATIC 1 - mode 3","notes":"C D E F# G G# A C","semitones":[0,2,4,6,7,8,9],"mode":"Enigmatic 1 - mode 3"},{"name":"ENIGMATIC 1 - mode 4","notes":"C D E F F# G Bb C","semitones":[0,2,4,5,6,7,10],"mode":"Enigmatic 1 - mode 4"},{"name":"ENIGMATIC 1 - mode 5","notes":"C D D# E F Ab Bb C","semitones":[0,2,3,4,5,8,10],"mode":"Enigmatic 1 - mode 5"},{"name":"ENIGMATIC 1 - mode 6","notes":"C C# D Eb Gb Ab Bb C","semitones":[0,1,2,3,6,8,10],"mode":"Enigmatic 1 - mode 6"},{"name":"ENIGMATIC 1 - mode 7","notes":"C C# D F G A B C","semitones":[0,1,2,5,7,9,11],"mode":"Enigmatic 1 - mode 7"},{"name":"ENIGMATIC 2","notes":"C Db E F Ab Bb B C","semitones":[0,1,4,5,8,10,11],"mode":"Enigmatic 2 - mode 1"},{"name":"ENIGMATIC 2 - mode 2","notes":"C D# E G A A# B C","semitones":[0,3,4,7,9,10,11],"mode":"Enigmatic 2 - mode 2"},{"name":"ENIGMATIC 2 - mode 3","notes":"C C# E F# G G# A C","semitones":[0,1,4,6,7,8,9],"mode":"Enigmatic 2 - mode 3"},{"name":"ENIGMATIC 2 - mode 4","notes":"C Eb F F# G Ab B C","semitones":[0,3,5,6,7,8,11],"mode":"Enigmatic 2 - mode 4"},{"name":"ENIGMATIC 2 - mode 5","notes":"C D D# E F G# A C","semitones":[0,2,3,4,5,8,9],"mode":"Enigmatic 2 - mode 5"},{"name":"ENIGMATIC 2 - mode 6","notes":"C C# D Eb F# G Bb C","semitones":[0,1,2,3,6,7,10],"mode":"Enigmatic 2 - mode 6"},{"name":"ENIGMATIC 2 - mode 7","notes":"C C# D F F# A B C","semitones":[0,1,2,5,6,9,11],"mode":"Enigmatic 2 - mode 7"},{"name":"BLUES SCALE","notes":"C Eb F F# G Bb C","semitones":[0,3,5,6,7,10],"mode":"Blues Scale - mode 1"},{"name":"MAJOR BLUES SCALE","notes":"C D Eb E G A C","semitones":[0,2,3,4,7,9],"mode":"Blues Scale - mode 2"},{"name":"BLUES SCALE - mode 3","notes":"C C# D F G Bb C","semitones":[0,1,2,5,7,10],"mode":"Blues Scale - mode 3"},{"name":"MARWA","notes":"C C# E F# A B C","semitones":[0,1,4,6,9,11],"mode":"Blues Scale - mode 4"},{"name":"BLUES SCALE - mode 5","notes":"C Eb F Ab Bb B C","semitones":[0,3,5,8,10,11],"mode":"Blues Scale - mode 5"},{"name":"BLUES SCALE - mode 6","notes":"C D F G G# A C","semitones":[0,2,5,7,8,9],"mode":"Blues Scale - mode 6"},{"name":"1 PROMETHEUS","notes":"C D E F# A Bb C","semitones":[0,2,4,6,9,10],"mode":"Prometheus - mode 1"},{"name":"2 PROMETHEUS - mode 2","notes":"C D E G Ab Bb C","semitones":[0,2,4,7,8,10],"mode":"Prometheus - mode 2"},{"name":"3 PROMETHEUS - mode 3","notes":"C D F Gb Ab Bb C","semitones":[0,2,5,6,8,10],"mode":"Prometheus - mode 3"},{"name":"4 PROMETHEUS - mode 4","notes":"C D# E F# Ab Bb C","semitones":[0,3,4,6,8,10],"mode":"Prometheus - mode 4"},{"name":"5 PROMETHEUS - mode 5","notes":"C Db Eb F G A C","semitones":[0,1,3,5,7,9],"mode":"Prometheus - mode 5"},{"name":"6 PROMETHEUS - mode 6","notes":"C D E F# G# B C","semitones":[0,2,4,6,8,11],"mode":"Prometheus - mode 6"},{"name":"SHO 1","notes":"C D Eb F G A C","semitones":[0,2,3,5,7,9],"mode":"Sho 1 - mode 1"},{"name":"SHO 1 - mode 2","notes":"C Db Eb F G Bb C","semitones":[0,1,3,5,7,10],"mode":"Sho 1 - mode 2"},{"name":"SHO 1 - mode 3","notes":"C D E F# A B C","semitones":[0,2,4,6,9,11],"mode":"Sho 1 - mode 3"},{"name":"SHO 1 - mode 4","notes":"C D E G A Bb C","semitones":[0,2,4,7,9,10],"mode":"Sho 1 - mode 4"},{"name":"SHO 1 - mode 5","notes":"C D F G Ab Bb C","semitones":[0,2,5,7,8,10],"mode":"Sho 1 - mode 5"},{"name":"SHO 1 - mode 6","notes":"C Eb F Gb Ab Bb C","semitones":[0,3,5,6,8,10],"mode":"Sho 1 - mode 6"},{"name":"SHO 2","notes":"C Db Eb Fb Gb Bb C","semitones":[0,1,3,4,6,10],"mode":"Sho 2 - mode 1"},{"name":"SHO 2 - mode 2","notes":"C D Eb F A B C","semitones":[0,2,3,5,9,11],"mode":"Sho 2 - mode 2"},{"name":"SHO 2 - mode 3","notes":"C Db Eb G A Bb C","semitones":[0,1,3,7,9,10],"mode":"Sho 2 - mode 3"},{"name":"SHO 2 - mode 4","notes":"C D F# G# A B C","semitones":[0,2,6,8,9,11],"mode":"Sho 2 - mode 4"},{"name":"SHO 2 - mode 5","notes":"C E F# G A Bb C","semitones":[0,4,6,7,9,10],"mode":"Sho 2 - mode 5"},{"name":"SHO 2 - mode 6","notes":"C D Eb F Gb Ab A","semitones":[0,2,3,5,6,8],"mode":"Sho 2 - mode 6"},{"name":"MAJOR PENTATONIC","notes":"C D E G A C","semitones":[0,2,4,7,9],"mode":"Major Pentatonic - mode 1"},{"name":"MAJOR PENTATONIC - mode 2","notes":"C D F G Bb C","semitones":[0,2,5,7,10],"mode":"Major Pentatonic - mode 2"},{"name":"MAJOR PENTATONIC - mode 3","notes":"C Eb F Ab Bb C","semitones":[0,3,5,8,10],"mode":"Major Pentatonic - mode 3"},{"name":"BANSHIKI-CHO","notes":"C D F G A C","semitones":[0,2,5,7,9],"mode":"Major Pentatonic - mode 4"},{"name":"MINOR PENTATONIC","notes":"C Eb F G Bb C","semitones":[0,3,5,7,10],"mode":"Major Pentatonic - mode 5"},{"name":"KANSAS CITY, KUMOI","notes":"C D Eb G A C","semitones":[0,2,3,7,9],"mode":"Kansas City - mode 1"},{"name":"IN SEN","notes":"C Db F G Bb C","semitones":[0,1,5,7,10],"mode":"Kansas City - mode 2"},{"name":"KANSAS CITY - mode 3","notes":"C E F# A B C","semitones":[0,4,6,9,11],"mode":"Kansas City - mode 3"},{"name":"KANSAS CITY - mode 4","notes":"C D F G Ab C","semitones":[0,2,5,7,8],"mode":"Kansas City - mode 4"},{"name":"KANSAS CITY - mode 5","notes":"C Eb F Gb Bb C","semitones":[0,3,5,6,10],"mode":"Kansas City - mode 5"},{"name":"AUGMENTED PENTATONIC, MAJOR PENTATONIC b6","notes":"C D E G Ab C","semitones":[0,2,4,7,8],"mode":"Augmented Pentatonic - mode 1"},{"name":"AUGMENTED PENTATONIC - mode 2","notes":"C D F Gb Bb C","semitones":[0,2,5,6,10],"mode":"Augmented Pentatonic - mode 2"},{"name":"ALTERED PENTATONIC","notes":"C Eb E Ab Bb C","semitones":[0,3,4,8,10],"mode":"Augmented Pentatonic - mode 3"},{"name":"AUGMENTED PENTATONIC - mode 4","notes":"C Db F G A C","semitones":[0,1,5,7,9],"mode":"Augmented Pentatonic - mode 4"},{"name":"AUGMENTED PENTATONIC - mode 5","notes":"C E F# G# B C","semitones":[0,4,6,8,11],"mode":"Augmented Pentatonic - mode 5"},{"name":"HIRAJOSHI, AKEBONO","notes":"C D Eb G Ab C","semitones":[0,2,3,7,8],"mode":"Kojo No Tsuki - mode 1"},{"name":"IWATO","notes":"C Db F Gb Bb C","semitones":[0,1,5,6,10],"mode":"Kojo No Tsuki - mode 2"},{"name":"KUMOI","notes":"C E F A B C","semitones":[0,4,5,9,11],"mode":"Kojo No Tsuki - mode 3"},{"name":"HON KUMOI SHIOUZHI","notes":"C Db F G Ab C","semitones":[0,1,5,7,8],"mode":"Kojo No Tsuki - mode 4"},{"name":"CHINESE, JAPANESE","notes":"C E F# G B C","semitones":[0,4,6,7,11],"mode":"Kojo No Tsuki - mode 5"},{"name":"PYGMY, YO","notes":"C D Eb G Bb C","semitones":[0,2,3,7,10],"mode":"Five Note Pygmy Scale of Rwanda - mode 1"},{"name":"PYGMY - mode 2","notes":"C Db F Ab Bb C","semitones":[0,1,5,8,10],"mode":"Five Note Pygmy Scale of Rwanda - mode 2"},{"name":"PGYMY - mode 3","notes":"C E G A B C","semitones":[0,4,7,9,11],"mode":"Five Note Pygmy Scale of Rwanda - mode 3"},{"name":"PGYMY - mode 4","notes":"C Eb F G Ab C","semitones":[0,3,5,7,8],"mode":"Five Note Pygmy Scale of Rwanda - mode 4"},{"name":"PGYMY - mode 5","notes":"C D E F A C","semitones":[0,2,4,5,9],"mode":"Five Note Pygmy Scale of Rwanda - mode 5"},{"name":"JOG","notes":"C D F# G A C","semitones":[0,2,6,7,9],"mode":"Jog - mode 1"},{"name":"JOG - mode 2","notes":"C E F G Bb C","semitones":[0,4,5,7,10],"mode":"Jog - mode 2"},{"name":"JOG - mode 3","notes":"C Db Eb Gb Ab Bb C","semitones":[0,1,3,6,8,10],"mode":"Jog - mode 3"},{"name":"JOG - mode 4","notes":"C D F G B C","semitones":[0,2,5,7,11],"mode":"Jog - mode 4"},{"name":"JOG - mode 5","notes":"C Eb F A Bb C","semitones":[0,3,5,9,10],"mode":"Jog - mode 5"},{"name":"HANSA DHWANI","notes":"C D E G B C","semitones":[0,2,4,7,11],"mode":"Hansa Dhwani - mode 1"},{"name":"HANSA DHWANI - mode 2","notes":"C D F A Bb C","semitones":[0,2,5,9,10],"mode":"Hansa Dhwani - mode 2"},{"name":"HANSA DHWANI - mode 3","notes":"C Eb G Ab Bb C","semitones":[0,3,7,8,10],"mode":"Hansa Dhwani - mode 3"},{"name":"HANSA DHWANI - mode 4","notes":"C E F G A C","semitones":[0,4,5,7,9],"mode":"Hansa Dhwani - mode 4"},{"name":"HANSA DHWANI - mode 5","notes":"C Db Eb F Ab C","semitones":[0,1,3,5,8],"mode":"Hansa Dhwani - mode 5"},{"name":"YUSEF SYNTHETIC 3","notes":"C D F F# G Bb B C","semitones":[0,2,5,6,7,10,11],"mode":"SYNTHETIC"},{"name":"YUSEF SYNTHETIC 3 - mode 2","notes":"C D# E F G# A Bb C","semitones":[0,3,4,5,8,9,10],"mode":"SYNTHETIC"},{"name":"YUSEF SYNTHETIC 3 - mode 3","notes":"C C# D F F# G A C","semitones":[0,1,2,5,6,7,9],"mode":"SYNTHETIC"},{"name":"YUSEF SYNTHETIC 3 - mode 4","notes":"C C# E F F# G# B C","semitones":[0,1,4,5,6,8,11],"mode":"SYNTHETIC"},{"name":"YUSEF SYNTHETIC 3 - mode 5","notes":"C D# E F G Bb B C","semitones":[0,3,4,5,7,10,11],"mode":"SYNTHETIC"},{"name":"YUSEF SYNTHETIC 3 - mode 6","notes":"C C# D E G G# A C","semitones":[0,1,2,4,7,8,9],"mode":"SYNTHETIC"},{"name":"YUSEF SYNTHETIC 3 - mode 7","notes":"C C# D# F# G G# B C","semitones":[0,1,3,6,7,8,11],"mode":"SYNTHETIC"},{"name":"YUSEF SYNTHETIC 5","notes":"C D Eb E G Ab Bb C","semitones":[0,2,3,4,7,8,10],"mode":"SYNTHETIC"},{"name":"YUSEF SYNTHETIC 5 - mode 2","notes":"C C# D F Gb Ab Bb C","semitones":[0,1,2,5,6,8,10],"mode":"SYNTHETIC"},{"name":"YUSEF SYNTHETIC 5 - mode 3","notes":"C C# E F G A B C","semitones":[0,1,4,5,7,9,11],"mode":"SYNTHETIC"},{"name":"YUSEF SYNTHETIC 5 - mode 4","notes":"C Eb Fb Gb Ab Bb B C","semitones":[0,3,4,6,8,10,11],"mode":"SYNTHETIC"},{"name":"YUSEF SYNTHETIC 5 - mode 5","notes":"C C# E F G A B C","semitones":[0,1,4,5,7,9,11],"mode":"SYNTHETIC"},{"name":"YUSEF SYNTHETIC 5 - mode 6","notes":"C Db Eb F G G# A C","semitones":[0,1,3,5,7,8,9],"mode":"SYNTHETIC"},{"name":"YUSEF SYNTHETIC 5 - mode 7","notes":"C D E F# G G# B C","semitones":[0,2,4,6,7,8,11],"mode":"SYNTHETIC"},{"name":"YUSEF SYNTHETIC 6","notes":"C D Eb E G G# A C","semitones":[0,2,3,4,7,8,9],"mode":"SYNTHETIC"},{"name":"YUSEF SYNTHETIC 6 - mode 2","notes":"C C# D F F# G Bb C","semitones":[0,1,2,5,6,7,10],"mode":"SYNTHETIC"},{"name":"YUSEF SYNTHETIC 6 - mode 3","notes":"C C# E F F# A B C","semitones":[0,1,4,5,6,9,11],"mode":"SYNTHETIC"},{"name":"YUSEF SYNTHETIC 6 - mode 4","notes":"C Eb E F Ab Bb B C","semitones":[0,3,4,5,8,10,11],"mode":"SYNTHETIC"},{"name":"YUSEF SYNTHETIC 6 - mode 5","notes":"C C# D F G G# A C","semitones":[0,1,2,5,7,8,9],"mode":"SYNTHETIC"},{"name":"YUSEF SYNTHETIC 6 - mode 6","notes":"C C# E F# G G# B C","semitones":[0,1,4,6,7,8,11],"mode":"SYNTHETIC"},{"name":"YUSEF SYNTHETIC 6 - mode 7","notes":"C Eb F F# G Bb B C","semitones":[0,3,5,6,7,10,11],"mode":"SYNTHETIC"},{"name":"YUSEF SYNTHETIC 8","notes":"C D Eb F G# A B C","semitones":[0,2,3,5,8,9,11],"mode":"SYNTHETIC"},{"name":"YUSEF SYNTHETIC 8 - mode 2","notes":"C Db Eb F# G A Bb C","semitones":[0,1,3,6,7,9,10],"mode":"SYNTHETIC"},{"name":"YUSEF SYNTHETIC 8 - mode 3","notes":"C D F F# G# A B C","semitones":[0,2,5,6,8,9,11],"mode":"SYNTHETIC"},{"name":"YUSEF SYNTHETIC 8 - mode 4","notes":"C D# E F# G A Bb C","semitones":[0,3,4,6,7,9,10],"mode":"SYNTHETIC"},{"name":"YUSEF SYNTHETIC 8 - mode 5","notes":"C C# D# E F# G A C","semitones":[0,1,3,4,6,7,9],"mode":"SYNTHETIC"},{"name":"YUSEF SYNTHETIC 8 - mode 6","notes":"C D Eb F F# G# B C","semitones":[0,2,3,5,6,8,11],"mode":"SYNTHETIC"},{"name":"YUSEF SYNTHETIC 8 - mode 7","notes":"C C# D# E F# G A C","semitones":[0,1,3,4,6,7,9],"mode":"SYNTHETIC"},{"name":"YUSEF SYNTHETIC 9","notes":"C C# D# E G# A B C","semitones":[0,1,3,4,8,9,11],"mode":"SYNTHETIC"},{"name":"YUSEF SYNTHETIC 9 - mode 2","notes":"C D Eb G Ab Bb B C","semitones":[0,2,3,7,8,10,11],"mode":"SYNTHETIC"},{"name":"YUSEF SYNTHETIC 9 - mode 3","notes":"C Db F F# G# A B C","semitones":[0,1,5,6,8,9,11],"mode":"SYNTHETIC"},{"name":"YUSEF SYNTHETIC 9 - mode 4","notes":"C E F G G# A B C","semitones":[0,4,5,7,8,9,11],"mode":"SYNTHETIC"},{"name":"YUSEF SYNTHETIC 9 - mode 5","notes":"C Db Eb E F G Ab C","semitones":[0,1,3,4,5,7,8],"mode":"SYNTHETIC"},{"name":"YUSEF SYNTHETIC 9 - mode 6","notes":"C D D# E F# G B C","semitones":[0,2,3,4,6,7,11],"mode":"SYNTHETIC"},{"name":"YUSEF SYNTHETIC 9 - mode 7","notes":"C C# D E F A Bb C","semitones":[0,1,2,4,5,9,10],"mode":"SYNTHETIC"},{"name":"YUSEF SYNTHETIC 10","notes":"C D F G Ab B C","semitones":[0,2,5,7,8,11],"mode":"SYNTHETIC"},{"name":"YUSEF SYNTHETIC 10 - mode 2","notes":"C Eb F Gb A Bb C","semitones":[0,3,5,6,9,10],"mode":"SYNTHETIC"},{"name":"YUSEF SYNTHETIC 10 - mode 3","notes":"C D Eb F# G A C","semitones":[0,2,3,6,7,9],"mode":"SYNTHETIC"},{"name":"YUSEF SYNTHETIC 10 - mode 4","notes":"C Db E F A Bb C","semitones":[0,1,4,5,9,10],"mode":"SYNTHETIC"},{"name":"YUSEF SYNTHETIC 10 - mode 5","notes":"C D# E F# A B C","semitones":[0,3,4,6,9,11],"mode":"SYNTHETIC"},{"name":"YUSEF SYNTHETIC 10 - mode 6","notes":"C Db Eb Gb Ab A C","semitones":[0,1,3,6,8,9],"mode":"SYNTHETIC"},{"name":"YUSEF SYNTHETIC 11 - mode 1","notes":"C Eb F# G B C","semitones":[0,3,6,7,11],"mode":"SYNTHETIC"},{"name":"YUSEF SYNTHETIC 11 - mode 2","notes":"C D# E G# A C","semitones":[0,3,4,8,9],"mode":"SYNTHETIC"},{"name":"YUSEF SYNTHETIC 11 - mode 3","notes":"C Db F F# A C","semitones":[0,1,5,6,9],"mode":"SYNTHETIC"},{"name":"YUSEF SYNTHETIC 11 - mode 4","notes":"C E F Ab B C","semitones":[0,4,5,8,11],"mode":"SYNTHETIC"},{"name":"YUSEF SYNTHETIC 11 - mode 5","notes":"C Db E G Ab C","semitones":[0,1,4,7,8],"mode":"SYNTHETIC"},{"name":"YUSEF SYNTHETIC 12","notes":"C E G Ab B C","semitones":[0,4,7,8,11],"mode":"SYNTHETIC"},{"name":"YUSEF SYNTHETIC 12 - mode 2","notes":"C D# E G Ab C","semitones":[0,3,4,7,8],"mode":"SYNTHETIC"},{"name":"YUSEF SYNTHETIC 12 - mode 3","notes":"C Db E F A C","semitones":[0,1,4,5,9],"mode":"SYNTHETIC"},{"name":"YUSEF SYNTHETIC 12 - mode 4","notes":"C D# E G# B C","semitones":[0,3,4,8,11],"mode":"SYNTHETIC"},{"name":"YUSEF SYNTHETIC 12 - mode 5","notes":"C Db F G# A C","semitones":[0,1,5,8,9],"mode":"SYNTHETIC"},{"name":"YUSEF SYNTHETIC 13","notes":"C Db F G# A C","semitones":[0,1,5,8,9],"mode":"SYNTHETIC"},{"name":"YUSEF SYNTHETIC 13 - mode 2","notes":"C E G Ab B C","semitones":[0,4,7,8,11],"mode":"SYNTHETIC"},{"name":"YUSEF SYNTHETIC 13 - mode 3","notes":"C D# E G Ab C","semitones":[0,3,4,7,8],"mode":"SYNTHETIC"},{"name":"YUSEF SYNTHETIC 13 - mode 4","notes":"C Db E F A C","semitones":[0,1,4,5,9],"mode":"SYNTHETIC"},{"name":"YUSEF SYNTHETIC 13 - mode 5","notes":"C D# E G# B C","semitones":[0,3,4,8,11],"mode":"SYNTHETIC"},{"name":"YUSEF SYNTHETIC 14","notes":"C F# A Bb B C","semitones":[0,6,9,10,11],"mode":"SYNTHETIC"},{"name":"YUSEF SYNTHETIC 14 - mode 2","notes":"C D# E F F# C","semitones":[0,3,4,5,6],"mode":"SYNTHETIC"},{"name":"YUSEF SYNTHETIC 14 - mode 3","notes":"C C# D Eb A C","semitones":[0,1,2,3,9],"mode":"SYNTHETIC"},{"name":"YUSEF SYNTHETIC 14 - mode 4","notes":"C C# D Ab B C","semitones":[0,1,2,8,11],"mode":"SYNTHETIC"},{"name":"YUSEF SYNTHETIC 14 - mode 5","notes":"C C# G Bb B C","semitones":[0,1,7,10,11],"mode":"SYNTHETIC"},{"name":"YUSEF SYNTHETIC 15","notes":"C Eb G A# B C","semitones":[0,3,7,10,11],"mode":"SYNTHETIC"},{"name":"YUSEF SYNTHETIC 15 - mode 2","notes":"C E G G# A C","semitones":[0,4,7,8,9],"mode":"SYNTHETIC"},{"name":"YUSEF SYNTHETIC 15 - mode 3","notes":"C D# E F Ab C","semitones":[0,3,4,5,8],"mode":"SYNTHETIC"},{"name":"YUSEF SYNTHETIC 15 - mode 4","notes":"C C# D F A C","semitones":[0,1,2,5,9],"mode":"SYNTHETIC"},{"name":"YUSEF SYNTHETIC 15 - mode 5","notes":"C C# E G# B C","semitones":[0,1,4,8,11],"mode":"SYNTHETIC"},{"name":"YUSEF SYNTHETIC 16","notes":"C Db Ab B C","semitones":[0,1,8,11],"mode":"SYNTHETIC"},{"name":"YUSEF SYNTHETIC 16 - mode 2","notes":"C G Bb B C","semitones":[0,7,10,11],"mode":"SYNTHETIC"},{"name":"YUSEF SYNTHETIC 16 - mode 3","notes":"C D# E F C","semitones":[0,3,4,5],"mode":"SYNTHETIC"},{"name":"YUSEF SYNTHETIC 16 - mode 4","notes":"C C# D A C","semitones":[0,1,2,9],"mode":"SYNTHETIC"},{"name":"YUSEF SYNTHETIC 17","notes":"C Db F Gb C","semitones":[0,1,5,6],"mode":"SYNTHETIC"},{"name":"YUSEF SYNTHETIC 17 - mode 2","notes":"C E F B C","semitones":[0,4,5,11],"mode":"SYNTHETIC"},{"name":"YUSEF SYNTHETIC 17 - mode 3","notes":"C Db G Ab C","semitones":[0,1,7,8],"mode":"SYNTHETIC"},{"name":"YUSEF SYNTHETIC 17 - mode 4","notes":"C F# G B C","semitones":[0,6,7,11],"mode":"SYNTHETIC"},{"name":"YUSEF SYNTHETIC 18","notes":"C Eb F Gb C","semitones":[0,3,5,6],"mode":"SYNTHETIC"},{"name":"YUSEF SYNTHETIC 18 - mode 2","notes":"C D Eb A C","semitones":[0,2,3,9],"mode":"SYNTHETIC"},{"name":"YUSEF SYNTHETIC 18 - mode 3","notes":"C Db G Bb C","semitones":[0,1,7,10],"mode":"SYNTHETIC"},{"name":"YUSEF SYNTHETIC 18 - mode 4","notes":"C F# A B C","semitones":[0,6,9,11],"mode":"SYNTHETIC"},{"name":"YUSEF SYNTHETIC 19","notes":"C E G Ab C","semitones":[0,4,7,8],"mode":"SYNTHETIC"},{"name":"YUSEF SYNTHETIC 19 - mode 2","notes":"C D# E Ab C","semitones":[0,3,4,8],"mode":"SYNTHETIC"},{"name":"YUSEF SYNTHETIC 19 - mode 3","notes":"C Db F A C","semitones":[0,1,5,9],"mode":"SYNTHETIC"},{"name":"YUSEF SYNTHETIC 19 - mode 4","notes":"C E G# B C","semitones":[0,4,8,11],"mode":"SYNTHETIC"},{"name":"YUSEF SYNTHETIC 20","notes":"C Db E F C","semitones":[0,1,4,5],"mode":"SYNTHETIC"},{"name":"YUSEF SYNTHETIC 20 - mode 2","notes":"C D# E B C","semitones":[0,3,4,11],"mode":"SYNTHETIC"},{"name":"YUSEF SYNTHETIC 20 - mode 3","notes":"C Db G# A C","semitones":[0,1,8,9],"mode":"SYNTHETIC"},{"name":"YUSEF SYNTHETIC 20 - mode 4","notes":"C G Ab B C","semitones":[0,7,8,11],"mode":"SYNTHETIC"},{"name":"AUGMENTED - mode 1","notes":"C D# E G Ab B C","semitones":[0,3,4,7,8,11],"mode":"SYMMETRICAL"},{"name":"AUGMENTED - mode 2","notes":"C Db E F G# A C","semitones":[0,1,4,5,8,9],"mode":"SYMMETRICAL"},{"name":"WHOLE TONE (messiaen 1)","notes":"C D E F# A Bb C","semitones":[0,2,4,6,9,10],"mode":"SYMMETRICAL, MESSIAEN"},{"name":"DIMINISHED 1 (messiaen 2 mode 1)","notes":"C C# D# E F# G A Bb C","semitones":[0,1,3,4,6,7,9,10],"mode":"SYMMETRICAL, MESSIAEN"},{"name":"DIMINISHED 2 (messiaen 2 mode 2)","notes":"C D Eb F F# G# A B C","semitones":[0,2,3,5,6,8,9,11],"mode":"SYMMETRICAL, MESSIAEN"},{"name":"MESSIAEN 3 - mode 1","notes":"C D D# E F# G G# A# B C","semitones":[0,2,3,4,6,7,8,10,11],"mode":"SYMMETRICAL, MESSIAEN"},{"name":"MESSIAEN 3 - mode 2","notes":"C C# D E F F# G# A Bb","semitones":[0,1,2,4,5,6,8,9],"mode":"SYMMETRICAL, MESSIAEN"},{"name":"MESSIAEN 3 - mode 3","notes":"C C# D# E F G G# A B C","semitones":[0,1,3,4,5,7,8,9,11],"mode":"SYMMETRICAL, MESSIAEN"},{"name":"MESSIAEN 4, YUSEF SYNTHETIC 1","notes":"C C# D F F# G G# B C","semitones":[0,1,2,5,6,7,8,11],"mode":"SYMMETRICAL, MESSIAEN"},{"name":"MESSIAEN 4 - mode 2","notes":"C C# E F F# G A# B C","semitones":[0,1,4,5,6,7,10,11],"mode":"SYMMETRICAL, MESSIAEN"},{"name":"MESSIAEN 4 - mode 3","notes":"C D# E F F# A A# B","semitones":[0,3,4,5,6,9,10],"mode":"SYMMETRICAL, MESSIAEN"},{"name":"MESSIAEN 4 - mode 4","notes":"C C# D D# F# G G# A C","semitones":[0,1,2,3,6,7,8,9],"mode":"SYMMETRICAL, MESSIAEN"},{"name":"MESSIAEN 5 - mode 1","notes":"C Db F F# G B C","semitones":[0,1,5,6,7,11],"mode":"SYMMETRICAL, MESSIAEN"},{"name":"MESSIAEN 5 - mode 2","notes":"C F E F# A# B C","semitones":[0,5,4,6,10,11],"mode":"SYMMETRICAL, MESSIAEN"},{"name":"TRITONE SEMI (messiaen 5 - mode 3)","notes":"C C# D F# G Ab C","semitones":[0,1,2,6,7,8],"mode":"SYMMETRICAL, MESSIAEN"},{"name":"MESSIAEN 6 - mode 1","notes":"C D E F F# G# A# B C","semitones":[0,2,4,5,6,8,10,11],"mode":"SYMMETRICAL, MESSIAEN"},{"name":"MESSIAEN 6 - mode 2","notes":"C D D# E F# G# A Bb C","semitones":[0,2,3,4,6,8,9,10],"mode":"SYMMETRICAL, MESSIAEN"},{"name":"MESSIAEN 6 - mode 3","notes":"C C# D E F# G Ab Bb C","semitones":[0,1,2,4,6,7,8,10],"mode":"SYMMETRICAL, MESSIAEN"},{"name":"MESSIAEN 6 - mode 4","notes":"C Db Eb F F# G A B C","semitones":[0,1,3,5,6,7,9,11],"mode":"SYMMETRICAL, MESSIAEN"},{"name":"MESSIAEN 7 - mode 1","notes":"C C# D Eb F F# G G# A B C","semitones":[0,1,2,3,5,6,7,8,9,11],"mode":"SYMMETRICAL, MESSIAEN"},{"name":"MESSIAEN 7 - mode 2","notes":"C C# D E F F# G G# A# B C","semitones":[0,1,2,4,5,6,7,8,10,11],"mode":"SYMMETRICAL, MESSIAEN"},{"name":"MESSIAEN 7 - mode 3","notes":"C C# D# E F F# G A A# B C","semitones":[0,1,3,4,5,6,7,9,10,11],"mode":"SYMMETRICAL, MESSIAEN"},{"name":"MESSIAEN 7 - mode 4","notes":"C D D# E F F# G# A A# B C","semitones":[0,2,3,4,5,6,8,9,10,11],"mode":"SYMMETRICAL, MESSIAEN"},{"name":"TRUNCATED MESSIAEN 2 mode 2 ver A - mode 1","notes":"C Eb F F# A B C","semitones":[0,3,5,6,9,11],"mode":"SYMMETRICAL, MESSIAEN"},{"name":"TRUNCATED MESSIAEN 2 mode 2 ver A - mode 2","notes":"C D Eb F# G# A C","semitones":[0,2,3,6,8,9],"mode":"SYMMETRICAL, MESSIAEN"},{"name":"TRITONE SCALE","notes":"C C# E F# G Bb C","semitones":[0,1,4,6,7,10],"mode":"SYMMETRICAL, MESSIAEN"},{"name":"TRUNCATED MESSIAEN 2 mode 2 ver B - mode 1","notes":"C D F F# G# B C","semitones":[0,2,5,6,8,11],"mode":"SYMMETRICAL, MESSIAEN"},{"name":"TRUNCATED MESSIAEN 2 mode 2 ver B - mode 2","notes":"C D# E F# A Bb C","semitones":[0,3,4,6,9,10],"mode":"SYMMETRICAL, MESSIAEN"},{"name":"TRUNCATED MESSIAEN 2 mode 2 ver B - mode 3","notes":"C Db Eb F# G A C","semitones":[0,1,3,6,7,9],"mode":"SYMMETRICAL, MESSIAEN"},{"name":"TRUNCATED MESSIAEN 5 - mode 1","notes":"C Db F# G C","semitones":[0,1,6,7],"mode":"SYMMETRICAL, MESSIAEN"},{"name":"TRUNCATED MESSIAEN 5 - mode 2","notes":"C F F# B C","semitones":[0,5,6,11],"mode":"SYMMETRICAL, MESSIAEN"}]
